tarea3/slave2.v
module slave2(
    input SCLK,
    input [15:0] MOSI,
    input CS,
    input [15:0] count_master,
    output reg [15:0] MISO
);

reg [1:0] termino = 0;
reg [15:0] count_slave = 16;
reg activador;

always @(posedge SCLK) begin //polaridad positiva

    if(count_slave != 0)
        if(count_master == 0)begin 
            activador = 1;
        end

        if(CS)begin
            termino <= termino + 1;
        end

        if(termino != 2)begin
            if(activador)begin
                MISO <= MOSI[count_slave - 1]; //little endian
                count_slave = count_slave - 1;
            end
        end
    end

endmodule

tarea3/slave1.v
module slave1(
    input SCLK,
    input [15:0] MOSI,
    input CS,
    input [15:0] count_master,
    output reg [15:0] MISO
);

reg [1:0] termino = 0;
reg [15:0] count_slave = 16;
reg activador;

always @(posedge SCLK) begin //polaridad positiva

    if(CS)begin
        termino <= termino + 1;
    end

    if(count_slave != 0)
        if(count_master == 0)begin 
            activador = 1;
        end

        if(termino != 2)begin
            if(activador)begin
                MISO <= MOSI[count_slave - 1]; //little endian
                count_slave = count_slave - 1;
            end
        end
    end

endmodule

tarea3/master.v
module master (
    input clk,
    input reset,
    input [15:0] MISO,
    input SLAVE_SELECT,
    input [15:0] datain,
    output reg CS_SLAVE1,
    output reg CS_SLAVE2,
    output reg SCLK,
    output reg [15:0] MOSI,
    output reg [15:0] count
);

reg [2:0] state;
reg [4:0] contador_final;

//parametros de estados
parameter inicioFinal = 0;
parameter inicioFinal_slave1 = 1;
parameter inicioFinal_slave2 = 2;
parameter cicloArribaSlave1 = 3;
parameter cicloAbajoSlave1 = 4;
parameter cicloArribaSlave2 = 5;
parameter cicloAbajoSlave2 = 6;

always @(negedge clk or posedge clk) begin
    if(reset) begin
        MOSI <= 16'b0;
        CS_SLAVE1 <= 1'b0;
        CS_SLAVE2 <= 1'b0;
        count <= 16'd16;
        SCLK <= 1'b0; //porque nada puede empezar hasta el CS no baje
        state <= 0;
        contador_final <= 0;
    
    end else begin
        case (state)
            inicioFinal : begin
                SCLK <= 0;
                state = SLAVE_SELECT ? inicioFinal_slave1 : inicioFinal_slave2;
            end 

            inicioFinal_slave1 : begin
                SCLK <= 0;
                CS_SLAVE1 <= 1;
                if(count == 0)begin
                    state <= inicioFinal;
                    CS_SLAVE1 <= 0;
                end 
                count <= 16;
                state <= cicloArribaSlave1;
            end 

            cicloArribaSlave1 :  begin
                SCLK <= 0;
                CS_SLAVE1 <= 0;
                MOSI <= datain[count - 1];
                count <= count - 1;
                state <= cicloAbajoSlave1;

            end
            cicloAbajoSlave1 : begin
                SCLK <= 1;
                if(count > 0) begin
                    state <= cicloArribaSlave1;
                end else begin
                    CS_SLAVE1 <= 1;
                    state <= inicioFinal_slave1;
                end
            end
            
            inicioFinal_slave2 : begin
                SCLK <= 0;
                if(contador_final == 31 || contador_final == 0)begin
                    CS_SLAVE2 <= 1;
                end
                state <= (contador_final == 31) ? inicioFinal_slave2 : cicloArribaSlave2;
            end 

            cicloArribaSlave2 :  begin
                SCLK <= 1;
                CS_SLAVE2 <= 0;
                contador_final = contador_final + 1;
                MOSI <= datain[count - 1];
                count <= count - 1;
                state <= cicloAbajoSlave2;

            end
            cicloAbajoSlave2 : begin
                SCLK <= 0;
                if(16 > count > 0) begin
                    state <= cicloArribaSlave2;
                end else begin
                    state <= inicioFinal_slave2;
                end
            end

            default: state <= inicioFinal;
        endcase
    end
end
    
endmodule

tarea3/top.v
`include "master.v"
`include "slave1.v"
`include "slave2.v"


module top (
    input clk,
    input reset,
    input SLAVE_SELECT,
    input [15:0] dataintop
);

// Interconexión de señales
wire [15:0] MOSI;
wire SCLK;
wire CS_SLAVE1;
wire CS_SLAVE2;
wire [15:0] count;
wire [15:0] MISO_SLAVE1;
wire [15:0] MISO_SLAVE2;
wire [15:0] MISO_MASTER;

// Selección de MISO del master basado en cuál slave está activo
assign MISO_MASTER = (SLAVE_SELECT) ? MISO_SLAVE1 : MISO_SLAVE2;

// Instancia del master
master master_inst (
    .clk(clk),
    .reset(reset),
    .MISO(MISO_MASTER),
    .SLAVE_SELECT(SLAVE_SELECT),
    .datain(dataintop),
    .CS_SLAVE1(CS_SLAVE1),
    .CS_SLAVE2(CS_SLAVE2),
    .SCLK(SCLK),
    .MOSI(MOSI),
    .count(count)
);

// Instancia del slave1
slave1 slave1_inst (
    .SCLK(SCLK),
    .MOSI(MOSI),
    .CS(CS_SLAVE1),
    .count_master(count),
    .MISO(MISO_SLAVE1)
);

// Instancia del slave2
slave2 slave2_inst (
    .SCLK(SCLK),
    .MOSI(MOSI),
    .CS(CS_SLAVE2),
    .count_master(count),
    .MISO(MISO_SLAVE2)
);

endmodule

tarea3/testbench.v
`include "top.v"

module tb_top;

    reg clk;
    reg reset;
    reg SLAVE_SELECT;
    reg [15:0] master_mosi;
    reg [15:0] datain_tb;

    // Instancia del módulo top
    top uut (
        .clk(clk),
        .reset(reset),
        .SLAVE_SELECT(SLAVE_SELECT),
        .dataintop(datain_tb)
    );

    // Generador de reloj
    always #5 clk = ~clk;

    initial begin
        $monitor("Time = %0t | clk = %b | reset = %b | SLAVE_SELECT = %b | state = %b | SCLK = %b | CS_SLAVE1 = %b | CS_SLAVE2 = %b | MOSI = %h | MISO_SLAVE1 = %h | MISO_SLAVE2 = %h",
                 $time, clk, reset, SLAVE_SELECT, uut.master_inst.state, uut.SCLK, uut.CS_SLAVE1, uut.CS_SLAVE2, uut.MOSI, uut.slave1_inst.MISO, uut.slave2_inst.MISO);
    end

    initial begin
        // Inicialización
        clk = 0;
        reset = 1;
        datain_tb = 16'hAAAA;
        
        // Esperar un ciclo de reloj
        #10;
        
        // Liberar reset
        reset = 0;
        
        #10
        // Simulación de selección de slave
        SLAVE_SELECT = 1; // Seleccionar slave 1
        #10
    
        #400;

        reset = 1;

        #20

        reset = 0;   
        SLAVE_SELECT = 0; // Seleccionar slave 2

        
        #400;
        
        // Finalizar simulación
        $finish;
    end

    initial begin
        $dumpfile("tb_top.vcd");
        $dumpvars(0, tb_top);
    end

endmodule

tarea3/tb_top.vcd
$date
	Fri Jun  7 21:13:58 2024
$end
$version
	Icarus Verilog
$end
$timescale
	1s
$end
$scope module tb_top $end
$var reg 1 ! SLAVE_SELECT $end
$var reg 1 " clk $end
$var reg 16 # datain_tb [15:0] $end
$var reg 1 $ reset $end
$scope module uut $end
$var wire 1 ! SLAVE_SELECT $end
$var wire 1 " clk $end
$var wire 16 % dataintop [15:0] $end
$var wire 1 $ reset $end
$var wire 16 & count [15:0] $end
$var wire 1 ' SCLK $end
$var wire 16 ( MOSI [15:0] $end
$var wire 16 ) MISO_SLAVE2 [15:0] $end
$var wire 16 * MISO_SLAVE1 [15:0] $end
$var wire 16 + MISO_MASTER [15:0] $end
$var wire 1 , CS_SLAVE2 $end
$var wire 1 - CS_SLAVE1 $end
$scope module master_inst $end
$var wire 16 . MISO [15:0] $end
$var wire 1 ! SLAVE_SELECT $end
$var wire 1 " clk $end
$var wire 16 / datain [15:0] $end
$var wire 1 $ reset $end
$var reg 1 - CS_SLAVE1 $end
$var reg 1 , CS_SLAVE2 $end
$var reg 16 0 MOSI [15:0] $end
$var reg 1 ' SCLK $end
$var reg 5 1 contador_final [4:0] $end
$var reg 16 2 count [15:0] $end
$var reg 3 3 state [2:0] $end
$upscope $end
$scope module slave1_inst $end
$var wire 1 - CS $end
$var wire 16 4 MOSI [15:0] $end
$var wire 1 ' SCLK $end
$var wire 16 5 count_master [15:0] $end
$var reg 16 6 MISO [15:0] $end
$var reg 1 7 activador $end
$var reg 16 8 count_slave [15:0] $end
$var reg 2 9 termino [1:0] $end
$upscope $end
$scope module slave2_inst $end
$var wire 1 , CS $end
$var wire 16 : MOSI [15:0] $end
$var wire 1 ' SCLK $end
$var wire 16 ; count_master [15:0] $end
$var reg 16 < MISO [15:0] $end
$var reg 1 = activador $end
$var reg 16 > count_slave [15:0] $end
$var reg 2 ? termino [1:0] $end
$upscope $end
$upscope $end
$upscope $end
$enddefinitions $end
#0
$dumpvars
b0 ?
b10000 >
x=
bx <
b10000 ;
b0 :
b0 9
b10000 8
x7
bx 6
b10000 5
b0 4
b0 3
b10000 2
b0 1
b0 0
b1010101010101010 /
bx .
0-
0,
bx +
bx *
bx )
b0 (
0'
b10000 &
b1010101010101010 %
1$
b1010101010101010 #
0"
0!
$end
#5
1"
#10
b10 3
0"
0$
#15
b101 3
1,
1"
#20
b110 3
b1111 &
b1111 2
b1111 5
b1111 ;
b1 (
b1 0
b1 4
b1 :
0,
1'
b1 1
0"
#25
b101 3
0'
1"
#30
b110 3
b1110 &
b1110 2
b1110 5
b1110 ;
b0 (
b0 0
b0 4
b0 :
1'
b10 1
0"
#35
b101 3
0'
1"
#40
b110 3
b1101 &
b1101 2
b1101 5
b1101 ;
b1 (
b1 0
b1 4
b1 :
1'
b11 1
0"
#45
b101 3
0'
1"
#50
b110 3
b1100 &
b1100 2
b1100 5
b1100 ;
b0 (
b0 0
b0 4
b0 :
1'
b100 1
0"
#55
b101 3
0'
1"
#60
b110 3
b1011 &
b1011 2
b1011 5
b1011 ;
b1 (
b1 0
b1 4
b1 :
1'
b101 1
0"
#65
b101 3
0'
1"
#70
b110 3
b1010 &
b1010 2
b1010 5
b1010 ;
b0 (
b0 0
b0 4
b0 :
1'
b110 1
0"
#75
b101 3
0'
1"
#80
b110 3
b1001 &
b1001 2
b1001 5
b1001 ;
b1 (
b1 0
b1 4
b1 :
1'
b111 1
0"
#85
b101 3
0'
1"
#90
b110 3
b1000 &
b1000 2
b1000 5
b1000 ;
b0 (
b0 0
b0 4
b0 :
1'
b1000 1
0"
#95
b101 3
0'
1"
#100
b110 3
b111 &
b111 2
b111 5
b111 ;
b1 (
b1 0
b1 4
b1 :
1'
b1001 1
0"
#105
b101 3
0'
1"
#110
b110 3
b110 &
b110 2
b110 5
b110 ;
b0 (
b0 0
b0 4
b0 :
1'
b1010 1
0"
#115
b101 3
0'
1"
#120
b110 3
b101 &
b101 2
b101 5
b101 ;
b1 (
b1 0
b1 4
b1 :
1'
b1011 1
0"
#125
b101 3
0'
1"
#130
b110 3
b100 &
b100 2
b100 5
b100 ;
b0 (
b0 0
b0 4
b0 :
1'
b1100 1
0"
#135
b101 3
0'
1"
#140
b110 3
b11 &
b11 2
b11 5
b11 ;
b1 (
b1 0
b1 4
b1 :
1'
b1101 1
0"
#145
b101 3
0'
1"
#150
b110 3
b10 &
b10 2
b10 5
b10 ;
b0 (
b0 0
b0 4
b0 :
1'
b1110 1
0"
#155
b101 3
0'
1"
#160
b110 3
b1 &
b1 2
b1 5
b1 ;
b1 (
b1 0
b1 4
b1 :
1'
b1111 1
0"
#165
b101 3
0'
1"
#170
b0 +
b0 .
b0 )
b0 <
b0 *
b0 6
b1111 >
1=
b1111 8
17
b110 3
b0 &
b0 2
b0 5
b0 ;
b0 (
b0 0
b0 4
b0 :
1'
b10000 1
0"
#175
b101 3
0'
1"
#180
b1110 8
b1110 >
b110 3
b1111111111111111 &
b1111111111111111 2
b1111111111111111 5
b1111111111111111 ;
b0x (
b0x 0
b0x 4
b0x :
1'
b10001 1
0"
#185
b10 3
0'
1"
#190
b101 3
0"
#195
b1101 >
b1101 8
b110 3
b1111111111111110 &
b1111111111111110 2
b1111111111111110 5
b1111111111111110 ;
1'
b10010 1
1"
#200
b10 3
0'
0"
#205
b101 3
1"
#210
b1100 8
b1100 >
b110 3
b1111111111111101 &
b1111111111111101 2
b1111111111111101 5
b1111111111111101 ;
1'
b10011 1
0"
#215
b10 3
0'
1"
#220
b101 3
0"
#225
b1011 >
b1011 8
b110 3
b1111111111111100 &
b1111111111111100 2
b1111111111111100 5
b1111111111111100 ;
1'
b10100 1
1"
#230
b10 3
0'
0"
#235
b101 3
1"
#240
b1010 8
b1010 >
b110 3
b1111111111111011 &
b1111111111111011 2
b1111111111111011 5
b1111111111111011 ;
1'
b10101 1
0"
#245
b10 3
0'
1"
#250
b101 3
0"
#255
b1001 >
b1001 8
b110 3
b1111111111111010 &
b1111111111111010 2
b1111111111111010 5
b1111111111111010 ;
1'
b10110 1
1"
#260
b10 3
0'
0"
#265
b101 3
1"
#270
b1000 8
b1000 >
b110 3
b1111111111111001 &
b1111111111111001 2
b1111111111111001 5
b1111111111111001 ;
1'
b10111 1
0"
#275
b10 3
0'
1"
#280
b101 3
0"
#285
b111 >
b111 8
b110 3
b1111111111111000 &
b1111111111111000 2
b1111111111111000 5
b1111111111111000 ;
1'
b11000 1
1"
#290
b10 3
0'
0"
#295
b101 3
1"
#300
b110 8
b110 >
b110 3
b1111111111110111 &
b1111111111110111 2
b1111111111110111 5
b1111111111110111 ;
1'
b11001 1
0"
#305
b10 3
0'
1"
#310
b101 3
0"
#315
b101 >
b101 8
b110 3
b1111111111110110 &
b1111111111110110 2
b1111111111110110 5
b1111111111110110 ;
1'
b11010 1
1"
#320
b10 3
0'
0"
#325
b101 3
1"
#330
b100 8
b100 >
b110 3
b1111111111110101 &
b1111111111110101 2
b1111111111110101 5
b1111111111110101 ;
1'
b11011 1
0"
#335
b10 3
0'
1"
#340
b101 3
0"
#345
b11 >
b11 8
b110 3
b1111111111110100 &
b1111111111110100 2
b1111111111110100 5
b1111111111110100 ;
1'
b11100 1
1"
#350
b10 3
0'
0"
#355
b101 3
1"
#360
b10 8
b10 >
b110 3
b1111111111110011 &
b1111111111110011 2
b1111111111110011 5
b1111111111110011 ;
1'
b11101 1
0"
#365
b10 3
0'
1"
#370
b101 3
0"
#375
b1 >
b1 8
b110 3
b1111111111110010 &
b1111111111110010 2
b1111111111110010 5
b1111111111110010 ;
1'
b11110 1
1"
#380
b10 3
0'
0"
#385
b101 3
1"
#390
b0x +
b0x .
b0x *
b0x 6
b0x )
b0x <
b0 8
b0 >
b110 3
b1111111111110001 &
b1111111111110001 2
b1111111111110001 5
b1111111111110001 ;
1'
b11111 1
0"
#395
b10 3
0'
1"
#400
1,
0"
#405
1"
#410
0"
#415
1"
#420
0"
#425
1"
#430
0"
#435
1"
#440
0"
#445
1"
#450
0"
1!
