tarea3/slave2.v
module slave2(
    input SCLK,
    input [15:0] MOSI,
    input CS,
    input [15:0] count_master,
    output reg [15:0] MISO
);

reg [15:0] count_slave = 16;
reg activador = 0;
reg [15:0] datos_guardados;

always @(posedge SCLK) begin
    if (CS) begin
        // Reiniciar variables cuando CS está activo
        count_slave <= 16;
        activador <= 0;
    end else begin
        // Capturar datos desde MOSI
        if (count_master <= 16) begin
            datos_guardados[count_master] <= MOSI;
        end 

        // Activar el envío de datos a MISO
        if (count_master == 0) begin
            activador <= 1;
        end

        if (activador) begin
            if (count_slave != 0) begin
                MISO <= datos_guardados[count_slave - 1]; // big endian
                count_slave <= count_slave - 1;
            end
        end
    end
end

endmodule

tarea3/slave1.v
module slave1(
    input SCLK,
    input [15:0] MOSI,
    input CS,
    input [15:0] count_master,
    output reg [15:0] MISO
);

reg [15:0] count_slave = 16;
reg activador = 0;
reg [15:0] datos_guardados;

always @(posedge SCLK) begin
    if (CS) begin
        // Reiniciar variables cuando CS está activo
        count_slave <= 16;
        activador <= 0;
    end else begin
        // Capturar datos desde MOSI
        if (count_master <= 16) begin
            datos_guardados[count_master] <= MOSI;
        end 

        // Activar el envío de datos a MISO
        if (count_master == 0) begin
            activador <= 1;
        end

        if (activador) begin
            if (count_slave != 0) begin
                MISO <= datos_guardados[count_slave - 1]; // Big endian
                count_slave <= count_slave - 1;
            end
        end
    end
end

endmodule

tarea3/master.v
module master (
    input clk,
    input reset,
    input [15:0] MISO,
    input SLAVE_SELECT,
    input [15:0] datain,
    output reg CS_SLAVE1,
    output reg CS_SLAVE2,
    output reg SCLK,
    output reg [15:0] MOSI,
    output reg [15:0] count
);

reg [2:0] state;
reg [5:0] contador_final;
reg [15:0] datos_recibidos;
reg [15:0] count_recibir;

//parametros de estados
parameter inicioFinal = 0;
parameter inicioFinal_slave1 = 1;
parameter inicioFinal_slave2 = 2;
parameter cicloArribaSlave1 = 3;
parameter cicloAbajoSlave1 = 4;
parameter cicloArribaSlave2 = 5;
parameter cicloAbajoSlave2 = 6;

always @(negedge clk or posedge clk) begin
    if(reset) begin
        MOSI <= 16'b0;
        CS_SLAVE1 <= 1'b0;
        CS_SLAVE2 <= 1'b0;
        count <= 16'd16;
        SCLK <= 1'b0; //porque nada puede empezar hasta el CS no baje
        state <= 0;
        contador_final <= 0;
        count_recibir <= 16;
        datos_recibidos <= 0;
        
    end else begin
        case (state)
            //Inicio para elegir el slave que se desea usar.
            inicioFinal : begin
                SCLK <= 0;
                state = SLAVE_SELECT ? inicioFinal_slave1 : inicioFinal_slave2;
            end 

            //estados necesarios para el slave 1
           
           inicioFinal_slave1 : begin
                SCLK <= 0;
                if(contador_final == 31 || contador_final == 0)begin
                    CS_SLAVE1 <= 1;
                end
                state <= (contador_final == 31) ? inicioFinal_slave1 : cicloArribaSlave1;
            end 

            cicloArribaSlave1 :  begin
                SCLK <= 1;
                CS_SLAVE1 <= 0;
                contador_final = contador_final + 1;
                MOSI <= datain[count - 1];
                count <= count - 1;
                state <= cicloAbajoSlave1;

            end
            cicloAbajoSlave1 : begin
                SCLK <= 0;
                if(16 > count > 0) begin
                    state <= cicloArribaSlave1;
                end else begin
                    state <= inicioFinal_slave1;
                end
            end
            
            //estados necesarios para el slave 2

            inicioFinal_slave2 : begin
                SCLK <= 0;
                if(contador_final == 32 || contador_final == 0)begin
                    CS_SLAVE2 <= 1;
                end
                state <= (contador_final == 32) ? inicioFinal_slave2 : cicloArribaSlave2;
            end 

            cicloArribaSlave2 :  begin
                SCLK <= 1;
                CS_SLAVE2 <= 0;
                contador_final = contador_final + 1;
                MOSI <= datain[count - 1];
                count <= count - 1;
                if(contador_final > 16)begin
                    datos_recibidos[count_recibir] <= MISO;
                    count_recibir = count_recibir - 1;
                end
                state <= cicloAbajoSlave2;

            end
            cicloAbajoSlave2 : begin
                SCLK <= 0;
                if(32 > contador_final > 0) begin
                    state <= cicloArribaSlave2;
                end else begin
                    state <= inicioFinal_slave2;
                end
            end

            default: state <= inicioFinal;
        endcase
    end
end
    
endmodule

tarea3/top.v
`include "master.v"
`include "slave1.v"
`include "slave2.v"


module top (
    input clk,
    input reset,
    input SLAVE_SELECT,
    input [15:0] dataintop
);

// Interconexión de señales
wire [15:0] MOSI;
wire SCLK;
wire CS_SLAVE1;
wire CS_SLAVE2;
wire [15:0] count;
wire [15:0] MISO_SLAVE1;
wire [15:0] MISO_SLAVE2;
wire [15:0] MISO_MASTER;

// Selección de MISO del master basado en cuál slave está activo
assign MISO_MASTER = (SLAVE_SELECT) ? MISO_SLAVE1 : MISO_SLAVE2;

// Instancia del master
master master_inst (
    .clk(clk),
    .reset(reset),
    .MISO(MISO_MASTER),
    .SLAVE_SELECT(SLAVE_SELECT),
    .datain(dataintop),
    .CS_SLAVE1(CS_SLAVE1),
    .CS_SLAVE2(CS_SLAVE2),
    .SCLK(SCLK),
    .MOSI(MOSI),
    .count(count)
);

// Instancia del slave1
slave1 slave1_inst (
    .SCLK(SCLK),
    .MOSI(MOSI),
    .CS(CS_SLAVE1),
    .count_master(count),
    .MISO(MISO_SLAVE1)
);

// Instancia del slave2
slave2 slave2_inst (
    .SCLK(SCLK),
    .MOSI(MOSI),
    .CS(CS_SLAVE2),
    .count_master(count),
    .MISO(MISO_SLAVE2)
);

endmodule

tarea3/testbench.v
`include "top.v"

module tb_top;

    reg clk;
    reg reset;
    reg SLAVE_SELECT;
    reg [15:0] master_mosi;
    reg [15:0] datain_tb;

    // Instancia del módulo top
    top uut (
        .clk(clk),
        .reset(reset),
        .SLAVE_SELECT(SLAVE_SELECT),
        .dataintop(datain_tb)
    );

    // Generador de reloj
    always #5 clk = ~clk;

    initial begin
        $monitor("Time = %0t | clk = %b | reset = %b | SLAVE_SELECT = %b | state = %b | SCLK = %b | CS_SLAVE1 = %b | CS_SLAVE2 = %b | MOSI = %h | MISO_SLAVE1 = %h | MISO_SLAVE2 = %h",
                 $time, clk, reset, SLAVE_SELECT, uut.master_inst.state, uut.SCLK, uut.CS_SLAVE1, uut.CS_SLAVE2, uut.MOSI, uut.slave1_inst.MISO, uut.slave2_inst.MISO);
    end

    initial begin
        // Inicialización
        clk = 0;
        reset = 1;
        datain_tb = 16'hAAAA;
        
        // Esperar un ciclo de reloj
        #10;
        
        // Liberar reset
        reset = 0;
        
        #10
        // Simulación de selección de slave
        SLAVE_SELECT = 1; // Seleccionar slave 1
        #10
    
        #400;

        reset = 1;

        #20

        reset = 0;   
        SLAVE_SELECT = 0; // Seleccionar slave 2

        
        #400;
        
        // Finalizar simulación
        $finish;
    end

    initial begin
        $dumpfile("tb_top.vcd");
        $dumpvars(0, tb_top);
    end

endmodule

tarea3/tb_top.vcd
$date
	Sun Jun  9 22:05:37 2024
$end
$version
	Icarus Verilog
$end
$timescale
	1s
$end
$scope module tb_top $end
$var reg 1 ! SLAVE_SELECT $end
$var reg 1 " clk $end
$var reg 16 # datain_tb [15:0] $end
$var reg 1 $ reset $end
$scope module uut $end
$var wire 1 ! SLAVE_SELECT $end
$var wire 1 " clk $end
$var wire 16 % dataintop [15:0] $end
$var wire 1 $ reset $end
$var wire 16 & count [15:0] $end
$var wire 1 ' SCLK $end
$var wire 16 ( MOSI [15:0] $end
$var wire 16 ) MISO_SLAVE2 [15:0] $end
$var wire 16 * MISO_SLAVE1 [15:0] $end
$var wire 16 + MISO_MASTER [15:0] $end
$var wire 1 , CS_SLAVE2 $end
$var wire 1 - CS_SLAVE1 $end
$scope module master_inst $end
$var wire 16 . MISO [15:0] $end
$var wire 1 ! SLAVE_SELECT $end
$var wire 1 " clk $end
$var wire 16 / datain [15:0] $end
$var wire 1 $ reset $end
$var reg 1 - CS_SLAVE1 $end
$var reg 1 , CS_SLAVE2 $end
$var reg 16 0 MOSI [15:0] $end
$var reg 1 ' SCLK $end
$var reg 6 1 contador_final [5:0] $end
$var reg 16 2 count [15:0] $end
$var reg 16 3 count_recibir [15:0] $end
$var reg 16 4 datos_recibidos [15:0] $end
$var reg 3 5 state [2:0] $end
$upscope $end
$scope module slave1_inst $end
$var wire 1 - CS $end
$var wire 16 6 MOSI [15:0] $end
$var wire 1 ' SCLK $end
$var wire 16 7 count_master [15:0] $end
$var reg 16 8 MISO [15:0] $end
$var reg 1 9 activador $end
$var reg 16 : count_slave [15:0] $end
$var reg 16 ; datos_guardados [15:0] $end
$upscope $end
$scope module slave2_inst $end
$var wire 1 , CS $end
$var wire 16 < MOSI [15:0] $end
$var wire 1 ' SCLK $end
$var wire 16 = count_master [15:0] $end
$var reg 16 > MISO [15:0] $end
$var reg 1 ? activador $end
$var reg 16 @ count_slave [15:0] $end
$var reg 16 A datos_guardados [15:0] $end
$upscope $end
$upscope $end
$upscope $end
$enddefinitions $end
#0
$dumpvars
bx A
b10000 @
0?
bx >
b10000 =
b0 <
bx ;
b10000 :
09
bx 8
b10000 7
b0 6
b0 5
b0 4
b10000 3
b10000 2
b0 1
b0 0
b1010101010101010 /
bx .
0-
0,
bx +
bx *
bx )
b0 (
0'
b10000 &
b1010101010101010 %
1$
b1010101010101010 #
0"
0!
$end
#5
1"
#10
b10 5
0"
0$
#15
b101 5
1,
1"
#20
b1xxxxxxxxxxxxxxx ;
b1xxxxxxxxxxxxxxx A
b110 5
b1111 &
b1111 2
b1111 7
b1111 =
b1 (
b1 0
b1 6
b1 <
0,
1'
b1 1
0"
#25
b101 5
0'
1"
#30
b10xxxxxxxxxxxxxx A
b10xxxxxxxxxxxxxx ;
b110 5
b1110 &
b1110 2
b1110 7
b1110 =
b0 (
b0 0
b0 6
b0 <
1'
b10 1
0"
#35
b101 5
0'
1"
#40
b101xxxxxxxxxxxxx ;
b101xxxxxxxxxxxxx A
b110 5
b1101 &
b1101 2
b1101 7
b1101 =
b1 (
b1 0
b1 6
b1 <
1'
b11 1
0"
#45
b101 5
0'
1"
#50
b1010xxxxxxxxxxxx A
b1010xxxxxxxxxxxx ;
b110 5
b1100 &
b1100 2
b1100 7
b1100 =
b0 (
b0 0
b0 6
b0 <
1'
b100 1
0"
#55
b101 5
0'
1"
#60
b10101xxxxxxxxxxx ;
b10101xxxxxxxxxxx A
b110 5
b1011 &
b1011 2
b1011 7
b1011 =
b1 (
b1 0
b1 6
b1 <
1'
b101 1
0"
#65
b101 5
0'
1"
#70
b101010xxxxxxxxxx A
b101010xxxxxxxxxx ;
b110 5
b1010 &
b1010 2
b1010 7
b1010 =
b0 (
b0 0
b0 6
b0 <
1'
b110 1
0"
#75
b101 5
0'
1"
#80
b1010101xxxxxxxxx ;
b1010101xxxxxxxxx A
b110 5
b1001 &
b1001 2
b1001 7
b1001 =
b1 (
b1 0
b1 6
b1 <
1'
b111 1
0"
#85
b101 5
0'
1"
#90
b10101010xxxxxxxx A
b10101010xxxxxxxx ;
b110 5
b1000 &
b1000 2
b1000 7
b1000 =
b0 (
b0 0
b0 6
b0 <
1'
b1000 1
0"
#95
b101 5
0'
1"
#100
b101010101xxxxxxx ;
b101010101xxxxxxx A
b110 5
b111 &
b111 2
b111 7
b111 =
b1 (
b1 0
b1 6
b1 <
1'
b1001 1
0"
#105
b101 5
0'
1"
#110
b1010101010xxxxxx A
b1010101010xxxxxx ;
b110 5
b110 &
b110 2
b110 7
b110 =
b0 (
b0 0
b0 6
b0 <
1'
b1010 1
0"
#115
b101 5
0'
1"
#120
b10101010101xxxxx ;
b10101010101xxxxx A
b110 5
b101 &
b101 2
b101 7
b101 =
b1 (
b1 0
b1 6
b1 <
1'
b1011 1
0"
#125
b101 5
0'
1"
#130
b101010101010xxxx A
b101010101010xxxx ;
b110 5
b100 &
b100 2
b100 7
b100 =
b0 (
b0 0
b0 6
b0 <
1'
b1100 1
0"
#135
b101 5
0'
1"
#140
b1010101010101xxx ;
b1010101010101xxx A
b110 5
b11 &
b11 2
b11 7
b11 =
b1 (
b1 0
b1 6
b1 <
1'
b1101 1
0"
#145
b101 5
0'
1"
#150
b10101010101010xx A
b10101010101010xx ;
b110 5
b10 &
b10 2
b10 7
b10 =
b0 (
b0 0
b0 6
b0 <
1'
b1110 1
0"
#155
b101 5
0'
1"
#160
b101010101010101x ;
b101010101010101x A
b110 5
b1 &
b1 2
b1 7
b1 =
b1 (
b1 0
b1 6
b1 <
1'
b1111 1
0"
#165
b101 5
0'
1"
#170
1?
b1010101010101010 A
19
b1010101010101010 ;
b110 5
b0 &
b0 2
b0 7
b0 =
b0 (
b0 0
b0 6
b0 <
1'
b10000 1
0"
#175
b101 5
0'
1"
#180
b1 +
b1 .
b1111 :
b1 *
b1 8
b1111 @
b1 )
b1 >
b110 5
b1111111111111111 &
b1111111111111111 2
b1111111111111111 7
b1111111111111111 =
b0x (
b0x 0
b0x 6
b0x <
1'
b1111 3
b10001 1
0"
#185
b101 5
0'
1"
#190
b0 +
b0 .
b1110 @
b0 )
b0 >
b1110 :
b0 *
b0 8
b110 5
b1000000000000000 4
b1111111111111110 &
b1111111111111110 2
b1111111111111110 7
b1111111111111110 =
1'
b1110 3
b10010 1
0"
#195
b101 5
0'
1"
#200
b1 +
b1 .
b1101 :
b1 *
b1 8
b1101 @
b1 )
b1 >
b110 5
b1111111111111101 &
b1111111111111101 2
b1111111111111101 7
b1111111111111101 =
1'
b1101 3
b10011 1
0"
#205
b101 5
0'
1"
#210
b0 +
b0 .
b1100 @
b0 )
b0 >
b1100 :
b0 *
b0 8
b110 5
b1010000000000000 4
b1111111111111100 &
b1111111111111100 2
b1111111111111100 7
b1111111111111100 =
1'
b1100 3
b10100 1
0"
#215
b101 5
0'
1"
#220
b1 +
b1 .
b1011 :
b1 *
b1 8
b1011 @
b1 )
b1 >
b110 5
b1111111111111011 &
b1111111111111011 2
b1111111111111011 7
b1111111111111011 =
1'
b1011 3
b10101 1
0"
#225
b101 5
0'
1"
#230
b0 +
b0 .
b1010 @
b0 )
b0 >
b1010 :
b0 *
b0 8
b110 5
b1010100000000000 4
b1111111111111010 &
b1111111111111010 2
b1111111111111010 7
b1111111111111010 =
1'
b1010 3
b10110 1
0"
#235
b101 5
0'
1"
#240
b1 +
b1 .
b1001 :
b1 *
b1 8
b1001 @
b1 )
b1 >
b110 5
b1111111111111001 &
b1111111111111001 2
b1111111111111001 7
b1111111111111001 =
1'
b1001 3
b10111 1
0"
#245
b101 5
0'
1"
#250
b0 +
b0 .
b1000 @
b0 )
b0 >
b1000 :
b0 *
b0 8
b110 5
b1010101000000000 4
b1111111111111000 &
b1111111111111000 2
b1111111111111000 7
b1111111111111000 =
1'
b1000 3
b11000 1
0"
#255
b101 5
0'
1"
#260
b1 +
b1 .
b111 :
b1 *
b1 8
b111 @
b1 )
b1 >
b110 5
b1111111111110111 &
b1111111111110111 2
b1111111111110111 7
b1111111111110111 =
1'
b111 3
b11001 1
0"
#265
b101 5
0'
1"
#270
b0 +
b0 .
b110 @
b0 )
b0 >
b110 :
b0 *
b0 8
b110 5
b1010101010000000 4
b1111111111110110 &
b1111111111110110 2
b1111111111110110 7
b1111111111110110 =
1'
b110 3
b11010 1
0"
#275
b101 5
0'
1"
#280
b1 +
b1 .
b101 :
b1 *
b1 8
b101 @
b1 )
b1 >
b110 5
b1111111111110101 &
b1111111111110101 2
b1111111111110101 7
b1111111111110101 =
1'
b101 3
b11011 1
0"
#285
b101 5
0'
1"
#290
b0 +
b0 .
b100 @
b0 )
b0 >
b100 :
b0 *
b0 8
b110 5
b1010101010100000 4
b1111111111110100 &
b1111111111110100 2
b1111111111110100 7
b1111111111110100 =
1'
b100 3
b11100 1
0"
#295
b101 5
0'
1"
#300
b1 +
b1 .
b11 :
b1 *
b1 8
b11 @
b1 )
b1 >
b110 5
b1111111111110011 &
b1111111111110011 2
b1111111111110011 7
b1111111111110011 =
1'
b11 3
b11101 1
0"
#305
b101 5
0'
1"
#310
b0 +
b0 .
b10 @
b0 )
b0 >
b10 :
b0 *
b0 8
b110 5
b1010101010101000 4
b1111111111110010 &
b1111111111110010 2
b1111111111110010 7
b1111111111110010 =
1'
b10 3
b11110 1
0"
#315
b101 5
0'
1"
#320
b1 +
b1 .
b1 :
b1 *
b1 8
b1 @
b1 )
b1 >
b110 5
b1111111111110001 &
b1111111111110001 2
b1111111111110001 7
b1111111111110001 =
1'
b1 3
b11111 1
0"
#325
b101 5
0'
1"
#330
b0 +
b0 .
b0 @
b0 )
b0 >
b0 :
b0 *
b0 8
b110 5
b1010101010101010 4
b1111111111110000 &
b1111111111110000 2
b1111111111110000 7
b1111111111110000 =
1'
b0 3
b100000 1
0"
#335
b10 5
0'
1"
#340
1,
0"
#345
1"
#350
0"
#355
1"
#360
0"
#365
1"
#370
0"
#375
1"
#380
0"
#385
1"
#390
0"
#395
1"
#400
0"
#405
1"
#410
0"
#415
1"
#420
0"
#425
1"
#430
0"
#435
1"
#440
0"
#445
1"
#450
0"
1!
