tarea2/tester.v
module tester(
    output reg clk, en, rst,
    output reg [7:0] a, b,
    output reg [1:0] MODO,
    input [7:0] c

);

always begin
#2  clk = ~clk;
end

initial begin
    //Valores iniciales
    clk = 0;
    en = 1;

    #8 //Esperar



    // Configuración para suma
    MODO = 2'b00; // Suma

    a = 8'h0A; // 10 en decimal
    b = 8'h05; // 5 en decimal
    #16; // Esperar

    // Configuración para suma
    a = 8'h09; // 10 en decimal
    b = 8'h03; // 5 en decimal
    #16; // Esperar

    en = 0; //haciendo reset
    rst = 1;

    #16//Esperar

    en = 1;//Quitando reset
    rst = 0;

    #16//Esperar

    // Configuración para resta
    MODO = 2'b01; // Resta

    a = 8'h0A; // 10 en decimal
    b = 8'h05; // 5 en decimal
    #16; // Esperar

    // Configuración para resta
    a = 8'h09; // 9 en decimal
    b = 8'h03; // 3 en decimal
    #16; // 
    
    en = 0; //haciendo reset
    rst = 1;

    #16//Esperar

    en = 1;//Quitando reset
    rst = 0;

    #16//Esperar

    // Configuración para multiplicacion
    MODO = 2'b10; // Multiplicacion

    a = 8'h0A; // 10 en decimal
    b = 8'h05; // 5 en decimal
    #16; // Esperar

    // Configuración para multiplicacion
    a = 8'h09; // 9 en decimal
    b = 8'h03; // 3 en decimal
    #16; // Esperar

    en = 0; //haciendo reset
    rst = 1;

    #16//Esperar

    en = 1;//Quitando reset
    rst = 0;

    #16//Esperar

    // Configuración para shift left
    MODO = 2'b11; // shiftleft

    a = 8'h0A; // 10 en decimal
    b = 8'h05; // 5 en decimal
    #16; // Esperar

    // Configuración para shiftleft
    b = 8'h03; // 3 en decimal
    a = 8'h09; // 9 en decimal
    #16; // Esperar

    en = 0; //haciendo reset
    rst = 1;

    #16//Esperar

    en = 1;//Quitando reset
    rst = 0;

    #16//Esperar

    
    $finish; // Finalizar simulación
  end

endmodule

tarea2/calculadora8bit.v
module calculadora8bit(
    input clk, en, rst,
    input [7:0] a, b, 
    input [1:0] MODO,
    output reg [7: 0] c
);

parameter SUMA = 2'b00;
parameter RESTA = 2'b01;
parameter MULTIPLICA = 2'b10;
parameter LEFTSHIFT = 2'b11;

always@(posedge clk)
begin
    if(en)begin
    case (MODO)
        SUMA: begin
            c <= a + b;
            end
        
        RESTA: begin
            c <= a - b;
                end
        
        MULTIPLICA: begin
            c <= a * b;
                    end

        LEFTSHIFT: begin
            c <= a >> b;
                    end

        default: 
            c <=0;

    endcase
    end
    if(rst)begin
        c <= 0;
    end
end
    
endmodule

tarea2/testbench.v
`include "calculadora8bit.v"
`include "tester.v"

module tb_;
    wire  clk, en, rst;
    wire [7:0] a, b, c;
    wire [1:0] MODO;

calculadora8bit DUT(
    .clk(clk),
    .rst(rst),
    .en(en),
    .a(a [7:0]),
    .b(b [7:0]),
    .MODO(MODO [1:0]),
    .c(c [7:0])
);

tester test(
    .clk(clk),
    .rst(rst),
    .en(en),
    .a(a),
    .b(b),
    .MODO(MODO),
    .c(c)
);

initial begin
    $dumpfile("tb_calculadora8bit.vcd");
    $dumpvars;
end


endmodule

tarea2/tb_calculadora8bit.vcd
$date
	Fri May  3 19:56:05 2024
$end
$version
	Icarus Verilog
$end
$timescale
	1s
$end
$scope module tb_ $end
$var wire 1 ! rst $end
$var wire 1 " en $end
$var wire 1 # clk $end
$var wire 8 $ c [7:0] $end
$var wire 8 % b [7:0] $end
$var wire 8 & a [7:0] $end
$var wire 2 ' MODO [1:0] $end
$scope module DUT $end
$var wire 1 ! rst $end
$var wire 1 " en $end
$var wire 1 # clk $end
$var wire 8 ( b [7:0] $end
$var wire 8 ) a [7:0] $end
$var wire 2 * MODO [1:0] $end
$var reg 8 + c [7:0] $end
$upscope $end
$scope module test $end
$var wire 8 , c [7:0] $end
$var reg 2 - MODO [1:0] $end
$var reg 8 . a [7:0] $end
$var reg 8 / b [7:0] $end
$var reg 1 # clk $end
$var reg 1 " en $end
$var reg 1 ! rst $end
$upscope $end
$upscope $end
$enddefinitions $end
#0
$dumpvars
bx /
bx .
bx -
bx ,
bx +
bx *
bx )
bx (
bx '
bx &
bx %
bx $
0#
1"
x!
$end
#2
b0 $
b0 +
b0 ,
1#
#4
0#
#6
1#
#8
0#
b101 %
b101 (
b101 /
b1010 &
b1010 )
b1010 .
b0 '
b0 *
b0 -
#10
b1111 $
b1111 +
b1111 ,
1#
#12
0#
#14
1#
#16
0#
#18
1#
#20
0#
#22
1#
#24
0#
b11 %
b11 (
b11 /
b1001 &
b1001 )
b1001 .
#26
b1100 $
b1100 +
b1100 ,
1#
#28
0#
#30
1#
#32
0#
#34
1#
#36
0#
#38
1#
#40
0#
1!
0"
#42
b0 $
b0 +
b0 ,
1#
#44
0#
#46
1#
#48
0#
#50
1#
#52
0#
#54
1#
#56
0#
0!
1"
#58
b1100 $
b1100 +
b1100 ,
1#
#60
0#
#62
1#
#64
0#
#66
1#
#68
0#
#70
1#
#72
0#
b101 %
b101 (
b101 /
b1010 &
b1010 )
b1010 .
b1 '
b1 *
b1 -
#74
b101 $
b101 +
b101 ,
1#
#76
0#
#78
1#
#80
0#
#82
1#
#84
0#
#86
1#
#88
0#
b11 %
b11 (
b11 /
b1001 &
b1001 )
b1001 .
#90
b110 $
b110 +
b110 ,
1#
#92
0#
#94
1#
#96
0#
#98
1#
#100
0#
#102
1#
#104
0#
1!
0"
#106
b0 $
b0 +
b0 ,
1#
#108
0#
#110
1#
#112
0#
#114
1#
#116
0#
#118
1#
#120
0#
0!
1"
#122
b110 $
b110 +
b110 ,
1#
#124
0#
#126
1#
#128
0#
#130
1#
#132
0#
#134
1#
#136
0#
b101 %
b101 (
b101 /
b1010 &
b1010 )
b1010 .
b10 '
b10 *
b10 -
#138
b110010 $
b110010 +
b110010 ,
1#
#140
0#
#142
1#
#144
0#
#146
1#
#148
0#
#150
1#
#152
0#
b11 %
b11 (
b11 /
b1001 &
b1001 )
b1001 .
#154
b11011 $
b11011 +
b11011 ,
1#
#156
0#
#158
1#
#160
0#
#162
1#
#164
0#
#166
1#
#168
0#
1!
0"
#170
b0 $
b0 +
b0 ,
1#
#172
0#
#174
1#
#176
0#
#178
1#
#180
0#
#182
1#
#184
0#
0!
1"
#186
b11011 $
b11011 +
b11011 ,
1#
#188
0#
#190
1#
#192
0#
#194
1#
#196
0#
#198
1#
#200
0#
b101 %
b101 (
b101 /
b1010 &
b1010 )
b1010 .
b11 '
b11 *
b11 -
#202
b0 $
b0 +
b0 ,
1#
#204
0#
#206
1#
#208
0#
#210
1#
#212
0#
#214
1#
#216
0#
b1001 &
b1001 )
b1001 .
b11 %
b11 (
b11 /
#218
b1 $
b1 +
b1 ,
1#
#220
0#
#222
1#
#224
0#
#226
1#
#228
0#
#230
1#
#232
0#
1!
0"
#234
b0 $
b0 +
b0 ,
1#
#236
0#
#238
1#
#240
0#
#242
1#
#244
0#
#246
1#
#248
0#
0!
1"
#250
b1 $
b1 +
b1 ,
1#
