laboratorio2/tester.v
/****************

Laboratorio 2 
Santiago Herra Castro C13721
Evelyn Feng Wu B82870
Circuitos Digitales II
Archivo: tester.v 
Prof. Ing. Ana Eugenia Sanchez Villalobos
Archivo: testbench.v une controlador.v y tester.v

Probador del controlador de tarjetas

*********************/

module tester(
    output reg clk,
    output reg rst,
    output reg tarjeta_recibida,
    output reg tipo_tarjeta,
    output reg [15:0] pin,
    output reg [3:0] digito,
    output reg digito_stb,
    output reg tipo_transaccion,
    output reg [31:0] monto,
    output reg monto_stb,

    input balance_actualizado, //se;al
    input entregar_dinero,
    input fondos_insuficientes,
    input pin_incorrecto,
    input bloqueo,
    input advertencia,
    input comision
);

always begin 
    #5 clk = ~clk;  
end
    initial begin
        clk=0;
        rst=0;
        tipo_tarjeta=0;
        tarjeta_recibida=0;
        tipo_tarjeta =0;
        pin=0;
        digito=0;
        digito_stb =0;
        monto=0;
        monto_stb =0;

    //caso1
    #10
    tarjeta_recibida=1;
    tipo_tarjeta=1; //cobra comision
     

    //pin: 6533 
    #10
    pin = 6;
    digito_stb=1;
    digito=6;
    #10
    digito_stb=0;
    #5
    pin = 5;
    digito_stb=1;
    digito=5;
    #10
    digito_stb=0;   
    #5
    pin = 3;
    digito_stb=1;
    digito=3;
    #10
    digito_stb=0;
    #5
    pin = 3;
    digito_stb=1;
    digito=3;
    #10
    digito_stb=0;
    //Se debe de aceptar el pin

    #20
    tipo_transaccion = 0;
    #10
    monto_stb = 1;
    monto = 2000;
    #10
    

    #50 //termina caso 1

    //Reset para comenzar caso 2
    rst=1;

    #20
    rst=0;
    #10

    //caso 2
    tarjeta_recibida=1;
    tipo_tarjeta=0; //no cobra comision
    pin=7129479238212222;
    //pone mal el pin 2 veces, pone el correcto y va a realizar un deposito    
    //pin 1 6539
    #10
    digito_stb=1;
    digito=6;
    #10
    digito_stb=0;
    #5
    digito_stb=1;
    digito=5;
    #10
    digito_stb=0;   
    #5
    digito_stb=1;
    digito=3;
    #10
    digito_stb=0;
    #5
    digito_stb=1;
    digito=3;
    #10
    digito_stb=0;
    //pin 2:1233
    #5
    digito_stb=1;
    digito=1;
    #10
    digito_stb=0;
    #5
    digito_stb=1;
    digito=2;
    #10
        digito_stb=0;
    #5
    digito_stb=1;
    digito=3;
    #10
        digito_stb=0;
    #5
    digito_stb=1;
    digito=3;
    #10
        digito_stb=0;
    #5
    //pin 3: correcto 2222
    digito_stb=1;
    digito=2;
    #10    
    digito_stb=0;
    #5
    digito_stb=1;
    digito=2;
    #10
        digito_stb=0;
    #5
    digito_stb=1;
    digito=2;
    #10
        digito_stb=0;
    #5
    digito_stb=1;
    digito=2;
    #10
        digito_stb=0;
    tipo_transaccion =0;
    monto_stb=1;
    monto=20000;
    #10
    monto_stb=0;
    #10
    rst=1;
        tipo_tarjeta=0;
        tarjeta_recibida=0;
        tipo_tarjeta =0;
        pin=0;
        digito=0;
        digito_stb =0;
        tipo_transaccion =0;
        monto=0;
        monto_stb =0;
    #10
    rst=0;
    

    //caso  3
    tarjeta_recibida=1;
    tipo_tarjeta=0; //no cobra comision
    pin=7192831732111123;
    //pone bien el pin y realiza retiro fondos insuficientes
    //pin : correcto 1123
    digito_stb=1;
    digito=1;
    #10    
    digito_stb=0;
    #5
    digito_stb=1;
    digito=1;
    #10
        digito_stb=0;
    #5
    digito_stb=1;
    digito=2;
    #10
        digito_stb=0;
    #5
    digito_stb=1;
    digito=3;
    #10
        digito_stb=0;
    tipo_transaccion =1;
    monto_stb=1;
    monto=60000;
    #10
    monto_stb=0;
    #10
    rst=1;
        tipo_tarjeta=0;
        tarjeta_recibida=0;
        tipo_tarjeta =0;
        pin=0;
        digito=0;
        digito_stb =0;
        tipo_transaccion =0;
        monto=0;
        monto_stb =0;
    #10
    rst=0;


    //caso  4
    tarjeta_recibida=1;
    tipo_tarjeta=1; //cobra comision
    pin=7192831732111123;
    //pone bien el pin y realiza retiro fondos insuficientes
    #10
        //pin: correcto 1123
    digito_stb=1;
    digito=1;
    #10    
    digito_stb=0;
    #5
    digito_stb=1;
    digito=1;
    #10
    digito_stb=0;
    #5
    digito_stb=1;
    digito=2;
    #10
    digito_stb=0;
    #5
    digito_stb=1;
    digito=3;
    #10
    digito_stb=0;
    tipo_transaccion =1;
    monto_stb=1;
    monto=20000;
    #10
    monto_stb=0;
    #10
    rst=1;
        tipo_tarjeta=0;
        tarjeta_recibida=0;
        tipo_tarjeta =0;
        pin=0;
        digito=0;
        digito_stb =0;
        tipo_transaccion =0;
        monto=0;
        monto_stb =0;
    $finish; 
    end
endmodule

laboratorio2/controlador.v
/****************

Laboratorio 2 
Santiago Herra Castro C13721
Evelyn Feng Wu B82870
Circuitos Digitales II
Archivo: controlador.v
Prof. Ing. Ana Eugenia Sanchez Villalobos
Archivo: testbench.v une controlador.v y tester.v

DUT de la Controlador de tarjetas del banco para retiros y depósitos

*********************/

module controlador(
    input clk,
    input rst,
    input tarjeta_recibida,
    input tipo_tarjeta,
    input [15:0] pin,
    input [3:0] digito,
    input digito_stb,
    input tipo_transaccion,
    input [31:0] monto,
    input monto_stb,

    output reg balance_actualizado, 
    output reg entregar_dinero,
    output reg fondos_insuficientes,
    output reg pin_incorrecto,
    output reg bloqueo,
    output reg advertencia,
    output reg comision
);


reg [63:0] balance = 5000; //valor de balance original
reg [2:0] contador_fallos; //cuenta fallos de bits
reg [2:0] contador_digitos; //cuenta los digitos de las veces que se acerto el pin
reg sigue_bucle = 1; //condicion para hacer break
integer j; //inetegers de for

//bloque de funcionamiento de reset
always@(posedge clk or negedge clk) begin
  if (rst) begin
    contador_digitos = 0;
    contador_fallos = 0;
    balance_actualizado = 0;
    entregar_dinero = 0;
    pin_incorrecto = 0;
    fondos_insuficientes = 0;
    bloqueo = 0;
    advertencia = 0;
    end   
end

//bloque always para las salidas del pin incorrecto
always@(posedge clk or negedge clk)begin
    if(contador_fallos == 1)begin 
        #10 pin_incorrecto = 1;
    end else if(contador_fallos == 2)begin
        #10 advertencia <= 1; //si falla 2 veces sale advertencia
    end else if(contador_fallos == 3) begin
        bloqueo <= 1;//si falla 3 veces sale bloqueo
        //reset <= 1; //preguntar como hacer para que reset tambien funcione como una salida
    end 
end


always@(posedge clk or negedge clk) begin
    if (tarjeta_recibida <= 1) begin
        if (tipo_tarjeta <= 1)
            comision = 1;

        
        for(j = 0; j < 4; j = j + 1)begin//Este es el for para que se repita la accion del digito 3 veces
            if(sigue_bucle)begin
                if(digito_stb)begin
                    if(digito == pin)begin //si el digito de entrada coincide con el carne
                        contador_digitos += 1;
                    end else begin //falle el acierto
                        contador_fallos += 1;
                    end
                    if(contador_fallos == 3)begin//si falla 3 veces se sale del blucle
                        sigue_bucle = 0;
                    end
                end
            end
        end

        if (!tipo_transaccion) begin //deposito
            if(monto_stb)begin //cuando se detecta la entrada de monton se ejecuta la acccion
                balance = balance + monto;
                balance_actualizado = 1;
            end
        end
        else if (tipo_transaccion)begin //retiro
            if(monto_stb)begin
                if (monto >= balance) begin
                    balance = balance - monto;
                    balance_actualizado = 1;
                    entregar_dinero = 1;
                    fondos_insuficientes = 0;
                end
                else begin
                    fondos_insuficientes = 1;
                    balance_actualizado = 0;
                end
            end
        end

    end
end    

endmodule

laboratorio2/testbench.v
`include "controlador.v"
`include "tester.v"

module tb;
    wire clk, rst, tarjeta_recibida, tipo_tarjeta;
    wire [15:0] pin;
    wire [3:0] digito;
    wire digito_stb, tipo_transaccion;
    wire [31:0] monto;
    wire monto_stb, balance_actualizado, entregar_dinero;
    wire fondos_insuficientes, pin_incorrecto, bloqueo, advertencia, comision;

controlador DUT(
    .clk(clk),
    .rst(rst),
    .tarjeta_recibida(tarjeta_recibida),
    .tipo_tarjeta(tipo_tarjeta),
    .pin(pin [15:0]),
    .digito(digito [3:0]),
    .digito_stb(digito_stb),
    .tipo_transaccion(tipo_transaccion),
    .monto(monto [31:0]),
    .monto_stb(monto_stb),
    .balance_actualizado(balance_actualizado),
    .entregar_dinero(entregar_dinero),
    .fondos_insuficientes(fondos_insuficientes),
    .pin_incorrecto(pin_incorrecto),
    .bloqueo(bloqueo),
    .advertencia(advertencia),
    .comision(comision)
);

tester test(
    .clk(clk),
    .rst(rst),
    .tarjeta_recibida(tarjeta_recibida),
    .tipo_tarjeta(tipo_tarjeta),
    .pin(pin [15:0]),
    .digito(digito [3:0]),
    .digito_stb(digito_stb),
    .tipo_transaccion(tipo_transaccion),
    .monto(monto [31:0]),
    .monto_stb(monto_stb),
    .balance_actualizado(balance_actualizado),
    .entregar_dinero(entregar_dinero),
    .fondos_insuficientes(fondos_insuficientes),
    .pin_incorrecto(pin_incorrecto),
    .bloqueo(bloqueo),
    .advertencia(advertencia),
    .comision(comision)
);


initial begin
    $dumpfile("gtk_controlador.vcd");
    $dumpvars;
end


endmodule

laboratorio2/gtk_controlador.vcd
$date
	Thu May 16 17:48:37 2024
$end
$version
	Icarus Verilog
$end
$timescale
	1s
$end
$scope module tb $end
$var wire 1 ! tipo_transaccion $end
$var wire 1 " tipo_tarjeta $end
$var wire 1 # tarjeta_recibida $end
$var wire 1 $ rst $end
$var wire 1 % pin_incorrecto $end
$var wire 16 & pin [15:0] $end
$var wire 1 ' monto_stb $end
$var wire 32 ( monto [31:0] $end
$var wire 1 ) fondos_insuficientes $end
$var wire 1 * entregar_dinero $end
$var wire 1 + digito_stb $end
$var wire 4 , digito [3:0] $end
$var wire 1 - comision $end
$var wire 1 . clk $end
$var wire 1 / bloqueo $end
$var wire 1 0 balance_actualizado $end
$var wire 1 1 advertencia $end
$scope module DUT $end
$var wire 1 ! tipo_transaccion $end
$var wire 1 " tipo_tarjeta $end
$var wire 1 # tarjeta_recibida $end
$var wire 1 $ rst $end
$var wire 16 2 pin [15:0] $end
$var wire 1 ' monto_stb $end
$var wire 32 3 monto [31:0] $end
$var wire 1 + digito_stb $end
$var wire 4 4 digito [3:0] $end
$var wire 1 . clk $end
$var reg 1 1 advertencia $end
$var reg 64 5 balance [63:0] $end
$var reg 1 0 balance_actualizado $end
$var reg 1 / bloqueo $end
$var reg 1 - comision $end
$var reg 3 6 contador_digitos [2:0] $end
$var reg 3 7 contador_fallos [2:0] $end
$var reg 1 * entregar_dinero $end
$var reg 1 ) fondos_insuficientes $end
$var reg 1 % pin_incorrecto $end
$var reg 1 8 sigue_bucle $end
$var integer 32 9 j [31:0] $end
$upscope $end
$scope module test $end
$var wire 1 1 advertencia $end
$var wire 1 0 balance_actualizado $end
$var wire 1 / bloqueo $end
$var wire 1 - comision $end
$var wire 1 * entregar_dinero $end
$var wire 1 ) fondos_insuficientes $end
$var wire 1 % pin_incorrecto $end
$var reg 1 . clk $end
$var reg 4 : digito [3:0] $end
$var reg 1 + digito_stb $end
$var reg 32 ; monto [31:0] $end
$var reg 1 ' monto_stb $end
$var reg 16 < pin [15:0] $end
$var reg 1 $ rst $end
$var reg 1 # tarjeta_recibida $end
$var reg 1 " tipo_tarjeta $end
$var reg 1 ! tipo_transaccion $end
$upscope $end
$upscope $end
$enddefinitions $end
#0
$dumpvars
b0 <
b0 ;
b0 :
b100 9
18
bx 7
bx 6
b1001110001000 5
b0 4
b0 3
b0 2
x1
x0
x/
0.
1-
b0 ,
0+
x*
x)
b0 (
0'
b0 &
x%
0$
0#
0"
x!
$end
#5
1.
#10
b100 9
0.
1"
1#
#15
1.
#20
b100 9
0.
b110 ,
b110 4
b110 :
1+
b110 &
b110 2
b110 <
#25
1.
#30
b100 9
0.
0+
#35
b100 9
1.
b101 ,
b101 4
b101 :
1+
b101 &
b101 2
b101 <
#40
0.
#45
b100 9
1.
0+
#50
b100 9
0.
b11 ,
b11 4
b11 :
1+
b11 &
b11 2
b11 <
#55
1.
#60
b100 9
0.
0+
#65
b100 9
1.
1+
#70
0.
#75
b100 9
1.
0+
#80
0.
#85
1.
#90
0.
#95
b100 9
1.
0!
#100
0.
#105
10
b1101101011000 5
b100 9
1.
b11111010000 (
b11111010000 3
b11111010000 ;
1'
#110
0.
#115
1.
#120
0.
#125
1.
#130
0.
#135
1.
#140
0.
#145
1.
#150
0.
#155
1.
#160
0.
#165
b10001100101000 5
b100 9
01
0/
0)
0%
0*
10
b0 7
b0 6
1.
1$
#170
00
0.
#175
1.
#180
0.
#185
1.
0$
#190
0.
#195
10
b10101011111000 5
b100 9
1.
b101101001111110 &
b101101001111110 2
b101101001111110 <
0"
#200
0.
#205
1/
b11001011001000 5
08
b11 7
b100 9
1.
b110 ,
b110 4
b110 :
1+
#210
0.
#215
b11101010011000 5
b100 9
1.
0+
#220
b100001001101000 5
b100 9
0.
b101 ,
b101 4
b101 :
1+
#225
1.
#230
b100101000111000 5
b100 9
0.
0+
#235
b101001000001000 5
b100 9
1.
b11 ,
b11 4
b11 :
1+
#240
0.
#245
b101100111011000 5
b100 9
1.
0+
#250
b110000110101000 5
b100 9
0.
1+
#255
1.
#260
b110100101111000 5
b100 9
0.
0+
#265
b111000101001000 5
b100 9
1.
b1 ,
b1 4
b1 :
1+
#270
0.
#275
b111100100011000 5
b100 9
1.
0+
#280
b1000000011101000 5
b100 9
0.
b10 ,
b10 4
b10 :
1+
#285
1.
#290
b1000100010111000 5
b100 9
0.
0+
#295
b1001000010001000 5
b100 9
1.
b11 ,
b11 4
b11 :
1+
#300
0.
#305
b1001100001011000 5
b100 9
1.
0+
#310
b1010000000101000 5
b100 9
0.
1+
#315
1.
#320
b1010011111111000 5
b100 9
0.
0+
#325
b1010111111001000 5
b100 9
1.
b10 ,
b10 4
b10 :
1+
#330
0.
#335
b1011011110011000 5
b100 9
1.
0+
#340
b1011111101101000 5
b100 9
0.
1+
#345
1.
#350
b1100011100111000 5
b100 9
0.
0+
#355
b1100111100001000 5
b100 9
1.
1+
#360
0.
#365
b1101011011011000 5
b100 9
1.
0+
#370
b1101111010101000 5
b100 9
0.
1+
#375
1.
#380
b10010110011001000 5
b100 9
0.
b100111000100000 (
b100111000100000 3
b100111000100000 ;
0+
#385
1.
#390
b100 9
0.
0'
#395
1.
#400
1/
00
b0 7
b100 9
0.
b0 (
b0 3
b0 ;
b0 ,
b0 4
b0 :
b0 &
b0 2
b0 <
0#
1$
#405
0/
1.
#410
b100 9
0.
b1 ,
b1 4
b1 :
1+
b101011100010011 &
b101011100010011 2
b101011100010011 <
1#
0$
#415
1.
#420
b100 9
0.
0+
#425
b100 9
1.
1+
#430
0.
#435
b100 9
1.
0+
#440
b100 9
0.
b10 ,
b10 4
b10 :
1+
#445
1.
#450
b100 9
0.
0+
#455
b100 9
1.
b11 ,
b11 4
b11 :
1+
#460
0.
#465
1)
b100 9
1.
b1110101001100000 (
b1110101001100000 3
b1110101001100000 ;
1'
1!
0+
#470
0.
#475
b100 9
1.
0'
#480
0.
#485
0)
b100 9
1.
b0 (
b0 3
b0 ;
0!
b0 ,
b0 4
b0 :
b0 &
b0 2
b0 <
0#
1$
#490
0.
#495
b100 9
1.
b101011100010011 &
b101011100010011 2
b101011100010011 <
1"
1#
0$
#500
0.
#505
b100 9
1.
b1 ,
b1 4
b1 :
1+
#510
0.
#515
b100 9
1.
0+
#520
b100 9
0.
1+
#525
1.
#530
b100 9
0.
0+
#535
b100 9
1.
b10 ,
b10 4
b10 :
1+
#540
0.
#545
b100 9
1.
0+
#550
b100 9
0.
b11 ,
b11 4
b11 :
1+
#555
1.
#560
1)
b100 9
0.
b100111000100000 (
b100111000100000 3
b100111000100000 ;
1'
1!
0+
#565
1.
#570
b100 9
0.
0'
#575
1.
#580
0)
b100 9
0.
b0 (
b0 3
b0 ;
0!
b0 ,
b0 4
b0 :
b0 &
b0 2
b0 <
0#
0"
1$
