laboratorio2/tester.v
/****************

Laboratorio 2 
Santiago Herra Castro C13721
Evelyn Feng Wu B82870
Circuitos Digitales II
Archivo: tester.v 
Prof. Ing. Ana Eugenia Sanchez Villalobos
Archivo: testbench.v une controlador.v y tester.v

Probador del controlador de tarjetas

*********************/

module tester(
    output reg clk,
    output reg rst,
    output reg tarjeta_recibida,
    output reg tipo_de_tarjeta,
    output reg [15:0] pin,
    output reg [3:0] digito,
    output reg digito_stb,
    output reg tipo_trans,
    output reg [31:0] monto,
    output reg monto_stb, 
    output reg entregar_dinero,
    output reg fondos_insuficientes,

    input balance_actualizado, //se;al
    input pin_incorrecto,
    input bloqueo,
    input advertencia,
    input comision
);

always begin 
    #5 clk = ~clk;  
end
    initial begin
    clk=0;
    rst=1;

    tipo_de_tarjeta=0;
    tarjeta_recibida=0;
    entregar_dinero=0;
    fondos_insuficientes=0;
    pin=0;
    digito=0;
    digito_stb =0;
    monto=0;
    monto_stb =0;
    
    #20
    rst=0;
    pin=16'b1101010011011101;
    //caso1: pin correcto
    #10
    tarjeta_recibida=1;
    tipo_de_tarjeta=1; //cobra comision
    #25
   
    digito=4'b1101; //digito 1
    #10
    digito_stb=1;
    #10
    digito_stb=0;
    #10
 
    digito=4'b0100; //digito 2
    #10
    digito_stb=1;
    #10
    digito_stb=0;   
    #10

    digito=4'b1101; //digito 3
    #10
    digito_stb=1;
    #10
    digito_stb=0;
    #10

    digito=4'b1101; //digito 4
    #10
    digito_stb=1;
    #10
    digito_stb=0;
    #10

    tipo_trans =0; //deposito
    monto=32'b000000000000100111000100000; //20000
    #10
    monto_stb=1;
    #10
    monto_stb =0;
    #40
    rst=1;
    digito = 0;
    monto = 0;
    tarjeta_recibida = 0;
    tipo_de_tarjeta = 0;

    #10
    rst=0;
    #10

    //Caso 2
    #10
    tarjeta_recibida=1;
    tipo_de_tarjeta = 0; //No cobra comision
    #25
   
    digito=4'b1101; //digito 1
    #10
    digito_stb=1;
    #10
    digito_stb=0;
    #10
 
    digito=4'b0100; //digito 2
    #10
    digito_stb=1;
    #10
    digito_stb=0;   
    #10

    digito=4'b1101; //digito 3
    #10
    digito_stb=1;
    #10
    digito_stb=0;
    #10

    digito=4'b1101; //digito 4
    #10
    digito_stb=1;
    #10
    digito_stb=0;
    #10

    tipo_trans = 1; //
    monto=32'b000000000000100111000100000; //20000
    #10
    monto_stb=1;
    #10
    monto_stb =0;
    #40

    rst=1;
    digito = 0;
    monto = 0;
    tarjeta_recibida = 0;
    tipo_de_tarjeta = 0;
    #10
    rst=0;
    #10

    //Caso 3
     #10
    tarjeta_recibida=1;
    tipo_de_tarjeta = 0; //No cobra comision
    #25
   
    digito=4'b1001; //digito 1
    #10
    digito_stb=1;
    #10
    digito_stb=0;
    #10
 
    digito=4'b0000; //digito 2
    #10
    digito_stb=1;
    #10
    digito_stb=0;   
    #10

    digito=4'b1001; //digito 3
    #10
    digito_stb=1;
    #10
    digito_stb=0;
    #10

    //Falla el ingreso del pin
    rst = 1;
    #50

    //Se terminan las pruebas.
    $finish; 
    end
endmodule

laboratorio2/controlador.v
/****************

Laboratorio 2 
Santiago Herra Castro C13721
Evelyn Feng Wu B82870
Circuitos Digitales II
Archivo: controlador.v
Prof. Ing. Ana Eugenia Sanchez Villalobos
Archivo: testbench.v une controlador.v y tester.v

DUT de la Controlador de tarjetas del banco para retiros y depósitos

*********************/
module controlador(
    input clk,
    input rst,
    input tarjeta_recibida,
    input tipo_de_tarjeta,
    input [15:0] pin,
    input [3:0] digito,
    input digito_stb,
    input tipo_trans,
    input [31:0] monto,
    input monto_stb,

    output reg balance_actualizado, //señal
    output reg entregar_dinero,
    output reg fondos_insuficientes,
    output reg pin_incorrecto,
    output reg bloqueo,
    output reg advertencia,
    output reg comision
);

// Comprueba que el pin es correcto
reg [2:0] correcto; 
// Valor de balance original 50.000
reg [63:0] balance = 50000; 
// Cuenta los intentos fallidos
reg [2:0] contador_fallos; 
// Cuenta la cantidad de dígitos ingresados
reg [2:0] contador_digitos; 

reg coincidencia;

// Bloque de funcionamiento de reset, inicializa en 0
always @(posedge clk) begin
    if (rst) begin
        balance_actualizado <= 0;
        entregar_dinero <= 0;
        fondos_insuficientes <= 0;
        pin_incorrecto <= 0;
        bloqueo <= 0;
        advertencia <= 0;
        comision <= 0;
        contador_digitos <= 0;
        contador_fallos <= 0;
        correcto <= 0;
        coincidencia = 0;
    end   
end

always @(*) begin
    if (tarjeta_recibida == 1 && tipo_de_tarjeta == 1) begin
        comision = 1;
    end else begin
        comision = 0;
    end

    if (correcto == 3'b100 && monto_stb) begin 
        if (tipo_trans == 1) begin
            if (monto > balance) begin
                fondos_insuficientes = 1;
            end else begin              
                balance = balance - monto;
                balance_actualizado = 1;
                entregar_dinero = 1;
            end
        end else if (!tipo_trans) begin
            balance = balance + monto;
            balance_actualizado = 1;
        end
    end

    if (digito_stb && contador_digitos != 4) begin
        contador_digitos = contador_digitos + 1;

        // Bandera para controlar si ya se encontró una coincidencia
        coincidencia = 0;
        for (integer i = 0; i < 4; i = i + 1) begin
            if (!coincidencia && pin[i*4 +: 4] == digito) begin // Comprueba cada 4 bits
                correcto = correcto + 1;
                coincidencia = 1; // Se ha encontrado una coincidencia
            end
        end
    end

    // Contador correcto es menor a 4 entonces pin incorrecto
    if (digito_stb && correcto != 4 && contador_digitos == 4) begin
            contador_fallos = contador_fallos + 1;
            pin_incorrecto = 1; // Salida 
            #10
            contador_digitos = 0;
            correcto = 0;
            pin_incorrecto = 0;
    end    

    // Con dos fallos se enciende advertencia
    if (contador_fallos == 2)
        advertencia = 1;

    // Bloquea si 3 intentos fallidos
    if (contador_fallos == 3) begin
        advertencia = 0;
        bloqueo = 1;
    end

    // Tercer intento incorrecto
    if (correcto != 4 && contador_digitos == 4 && contador_fallos == 2) begin
        pin_incorrecto = 1;
        advertencia = 1;
        contador_fallos = contador_fallos + 1;
        #10
        pin_incorrecto = 0;
        advertencia = 0;     
        bloqueo = 1;   
        contador_digitos = 0;
        correcto = 0;     
    end    
end

always@(posedge clk or negedge clk)begin
    if(contador_fallos == 1)begin
        pin_incorrecto <= 1;
    end else if(contador_fallos == 2)begin
        advertencia <= 1; //si falla 2 veces sale advertencia
    end 
    else if(contador_fallos == 3) begin
        bloqueo <= 1;//si falla 3 veces sale bloqueo

    end 
end

endmodule

laboratorio2/testbench.v
`include "controlador.v"
`include "tester.v"

module tb;
    wire clk, rst, tarjeta_recibida, tipo_de_tarjeta;
    wire [15:0] pin;
    wire [3:0] digito;
    wire digito_stb, tipo_trans;
    wire [31:0] monto;
    wire monto_stb, balance_actualizado, entregar_dinero;
    wire fondos_insuficientes, pin_incorrecto, bloqueo, advertencia, comision;

controlador DUT(
    .clk(clk),
    .rst(rst),
    .tarjeta_recibida(tarjeta_recibida),
    .tipo_de_tarjeta(tipo_de_tarjeta),
    .pin(pin [15:0]),
    .digito(digito [3:0]),
    .digito_stb(digito_stb),
    .tipo_trans(tipo_trans),
    .monto(monto [31:0]),
    .monto_stb(monto_stb),
    .balance_actualizado(balance_actualizado),
    .entregar_dinero(entregar_dinero),
    .fondos_insuficientes(fondos_insuficientes),
    .pin_incorrecto(pin_incorrecto),
    .bloqueo(bloqueo),
    .advertencia(advertencia),
    .comision(comision)
);

tester test(
    .clk(clk),
    .rst(rst),
    .tarjeta_recibida(tarjeta_recibida),
    .tipo_de_tarjeta(tipo_de_tarjeta),
    .pin(pin [15:0]),
    .digito(digito [3:0]),
    .digito_stb(digito_stb),
    .tipo_trans(tipo_trans),
    .monto(monto [31:0]),
    .monto_stb(monto_stb),
    .balance_actualizado(balance_actualizado),
    .entregar_dinero(entregar_dinero),
    .fondos_insuficientes(fondos_insuficientes),
    .pin_incorrecto(pin_incorrecto),
    .bloqueo(bloqueo),
    .advertencia(advertencia),
    .comision(comision)
);


initial begin
    $dumpfile("gtk_controlador.vcd");
    $dumpvars;
end


endmodule

laboratorio2/gtk_controlador.vcd
$date
	Fri May 17 15:26:53 2024
$end
$version
	Icarus Verilog
$end
$timescale
	1s
$end
$scope module tb $end
$var wire 1 ! entregar_dinero $end
$var wire 1 " fondos_insuficientes $end
$var wire 1 # tipo_trans $end
$var wire 1 $ tipo_de_tarjeta $end
$var wire 1 % tarjeta_recibida $end
$var wire 1 & rst $end
$var wire 1 ' pin_incorrecto $end
$var wire 16 ( pin [15:0] $end
$var wire 1 ) monto_stb $end
$var wire 32 * monto [31:0] $end
$var wire 1 + digito_stb $end
$var wire 4 , digito [3:0] $end
$var wire 1 - comision $end
$var wire 1 . clk $end
$var wire 1 / bloqueo $end
$var wire 1 0 balance_actualizado $end
$var wire 1 1 advertencia $end
$scope module DUT $end
$var wire 1 # tipo_trans $end
$var wire 1 $ tipo_de_tarjeta $end
$var wire 1 % tarjeta_recibida $end
$var wire 1 & rst $end
$var wire 16 2 pin [15:0] $end
$var wire 1 ) monto_stb $end
$var wire 32 3 monto [31:0] $end
$var wire 1 + digito_stb $end
$var wire 4 4 digito [3:0] $end
$var wire 1 . clk $end
$var reg 1 1 advertencia $end
$var reg 64 5 balance [63:0] $end
$var reg 1 0 balance_actualizado $end
$var reg 1 / bloqueo $end
$var reg 1 6 coincidencia $end
$var reg 1 - comision $end
$var reg 3 7 contador_digitos [2:0] $end
$var reg 3 8 contador_fallos [2:0] $end
$var reg 3 9 correcto [2:0] $end
$var reg 1 : entregar_dinero $end
$var reg 1 ; fondos_insuficientes $end
$var reg 1 ' pin_incorrecto $end
$scope begin $ivl_for_loop0 $end
$var integer 32 < i [31:0] $end
$upscope $end
$upscope $end
$scope module test $end
$var wire 1 1 advertencia $end
$var wire 1 0 balance_actualizado $end
$var wire 1 / bloqueo $end
$var wire 1 - comision $end
$var wire 1 ' pin_incorrecto $end
$var reg 1 . clk $end
$var reg 4 = digito [3:0] $end
$var reg 1 + digito_stb $end
$var reg 1 > entregar_dinero $end
$var reg 1 ? fondos_insuficientes $end
$var reg 32 @ monto [31:0] $end
$var reg 1 ) monto_stb $end
$var reg 16 A pin [15:0] $end
$var reg 1 & rst $end
$var reg 1 % tarjeta_recibida $end
$var reg 1 $ tipo_de_tarjeta $end
$var reg 1 # tipo_trans $end
$upscope $end
$upscope $end
$enddefinitions $end
#0
$dumpvars
b0 A
b0 @
0?
0>
b0 =
bx <
x;
x:
bx 9
bx 8
bx 7
x6
b1100001101010000 5
b0 4
b0 3
b0 2
x1
x0
x/
0.
0-
b0 ,
0+
b0 *
0)
b0 (
x'
1&
0%
0$
x#
x"
x!
$end
#5
b0 9
b0 8
b0 7
01
0/
0'
0"
0;
0!
0:
00
06
1.
#10
0.
#15
1.
#20
0.
b1101010011011101 (
b1101010011011101 2
b1101010011011101 A
0&
#25
1.
#30
1-
0.
1$
1%
#35
1.
#40
0.
#45
1.
#50
0.
#55
1.
b1101 ,
b1101 4
b1101 =
#60
0.
#65
16
b1 9
b100 <
b1 7
1.
1+
#70
0.
#75
1.
0+
#80
0.
#85
1.
b100 ,
b100 4
b100 =
#90
0.
#95
b10 9
b100 <
16
b10 7
1.
1+
#100
0.
#105
1.
0+
#110
0.
#115
1.
b1101 ,
b1101 4
b1101 =
#120
0.
#125
b11 9
b100 <
16
b11 7
1.
1+
#130
0.
#135
1.
0+
#140
0.
#145
1.
#150
0.
#155
b100 9
b100 <
16
b100 7
1.
1+
#160
0.
#165
1.
0+
#170
0.
#175
1.
b100111000100000 *
b100111000100000 3
b100111000100000 @
0#
#180
0.
#185
10
b10001000101110000 5
1.
1)
#190
0.
#195
1.
0)
#200
0.
#205
1.
#210
0.
#215
1.
#220
0.
#225
1.
#230
0.
#235
b0 9
b0 7
00
06
0-
1.
0$
0%
b0 *
b0 3
b0 @
b0 ,
b0 4
b0 =
1&
#240
0.
#245
1.
0&
#250
0.
#255
1.
#260
0.
#265
1.
1%
#270
0.
#275
1.
#280
0.
#285
1.
#290
0.
b1101 ,
b1101 4
b1101 =
#295
1.
#300
16
b1 9
b100 <
b1 7
0.
1+
#305
1.
#310
0.
0+
#315
1.
#320
0.
b100 ,
b100 4
b100 =
#325
1.
#330
b10 9
b100 <
16
b10 7
0.
1+
#335
1.
#340
0.
0+
#345
1.
#350
0.
b1101 ,
b1101 4
b1101 =
#355
1.
#360
b11 9
b100 <
16
b11 7
0.
1+
#365
1.
#370
0.
0+
#375
1.
#380
0.
#385
1.
#390
b100 9
b100 <
16
b100 7
0.
1+
#395
1.
#400
0.
0+
#405
1.
#410
0.
b100111000100000 *
b100111000100000 3
b100111000100000 @
1#
#415
1.
#420
x!
1:
10
b1100001101010000 5
0.
1)
#425
1.
#430
0.
0)
#435
1.
#440
0.
#445
1.
#450
0.
#455
1.
#460
0.
#465
1.
#470
0.
0%
b0 *
b0 3
b0 @
b0 ,
b0 4
b0 =
1&
#475
b0 9
b0 7
0!
0:
00
06
1.
#480
0.
0&
#485
1.
#490
0.
#495
1.
#500
0.
1%
#505
1.
#510
0.
#515
1.
#520
0.
#525
1.
b1001 ,
b1001 4
b1001 =
#530
0.
#535
b100 <
b1 7
1.
1+
#540
0.
#545
1.
0+
#550
0.
#555
1.
b0 ,
b0 4
b0 =
#560
0.
#565
b100 <
b10 7
1.
1+
#570
0.
#575
1.
0+
#580
0.
#585
1.
b1001 ,
b1001 4
b1001 =
#590
0.
#595
b100 <
b11 7
1.
1+
#600
0.
#605
1.
0+
#610
0.
#615
b0 7
1.
1&
